cosl/__init__.py
cosl/cos_tool.py
cosl/grafana_dashboard.py
cosl/juju_topology.py
cosl/loki_logger.py
cosl/mandatory_relation_pairs.py
cosl/py.typed
cosl/reconciler.py
cosl/rules.py
cosl/time_validation.py
cosl/types.py
cosl/coordinated_workers/__init__.py
cosl/interfaces/__init__.py
cosl/interfaces/datasource_exchange.py
cosl/interfaces/utils.py
cosl-1.3.1.dist-info/METADATA
cosl-1.3.1.dist-info/WHEEL
cosl-1.3.1.dist-info/licenses/LICENSE
cosl-1.3.1.dist-info/RECORD
