Metadata-Version: 2.4
Name: cosl
Version: 1.3.1
Summary: Utils for COS Lite charms
Project-URL: Homepage, https://github.com/canonical/cos-lib
Project-URL: Bug Tracker, https://github.com/canonical/cos-lib/issues
Author-email: sed-i <82407168+sed-i@users.noreply.github.com>
License:                                  Apache License
License-File: LICENSE
Classifier: Development Status :: 4 - Beta
Classifier: Intended Audience :: Developers
Classifier: Intended Audience :: System Administrators
Classifier: License :: OSI Approved :: Apache Software License
Classifier: Operating System :: OS Independent
Classifier: Programming Language :: Python :: 3.8
Classifier: Topic :: Utilities
Classifier: Typing :: Typed
Requires-Python: >=3.8
Requires-Dist: ops
Requires-Dist: pydantic
Requires-Dist: pyyaml
Requires-Dist: tenacity
Requires-Dist: typing-extensions
